pnap_tag_api/__init__.py
pnap_tag_api/api_client.py
pnap_tag_api/api_response.py
pnap_tag_api/configuration.py
pnap_tag_api/exceptions.py
pnap_tag_api/py.typed
pnap_tag_api/rest.py
pnap_tag_api/version.py
pnap_tag_api/api/__init__.py
pnap_tag_api/api/tags_api.py
pnap_tag_api/models/__init__.py
pnap_tag_api/models/delete_result.py
pnap_tag_api/models/error.py
pnap_tag_api/models/resource_assignment.py
pnap_tag_api/models/tag.py
pnap_tag_api/models/tag_create.py
pnap_tag_api/models/tag_update.py
pnap_tag_api-2.0.4.dist-info/METADATA
pnap_tag_api-2.0.4.dist-info/WHEEL
pnap_tag_api-2.0.4.dist-info/top_level.txt
pnap_tag_api-2.0.4.dist-info/RECORD
